machbaseAPI/__init__.py
machbaseAPI/conntest.py
machbaseAPI/machbaseAPI.py
machbaseAPI/lib/libmachbaseAPI_arm64.dylib
machbaseAPI/lib/libmachbaseAPI_arm64.so
machbaseAPI/lib/libmachbaseAPI_x64.dylib
machbaseAPI/lib/libmachbaseAPI_x64.so
machbaseAPI/lib/machbaseAPI_x64.dll
machbaseAPI/sample/ConnTest.py
machbaseAPI/sample/MakeData.py
machbaseAPI/sample/Sample1Connect.py
machbaseAPI/sample/Sample2Simple.py
machbaseAPI/sample/Sample3Append.py
machbaseAPI/sample/Sample4Fetch.py
machbaseAPI/sample/Sample5Append2.py
machbaseAPI/sample/Sample5ConnectEx.py
machbaseAPI/sample/data.txt
machbaseAPI-1.12.dist-info/METADATA
machbaseAPI-1.12.dist-info/WHEEL
machbaseAPI-1.12.dist-info/top_level.txt
machbaseAPI-1.12.dist-info/RECORD
