Metadata-Version: 2.1
Name: machbaseAPI
Version: 1.12
Summary: Machbase-Python3-API
Home-page: http://www.machbase.com
Author: machbase
Author-email: support@machbase.com
License: UNKNOWN
Platform: UNKNOWN
Classifier: Programming Language :: Python :: 3
Classifier: License :: OSI Approved :: MIT License
Classifier: Operating System :: POSIX :: Linux
Classifier: Operating System :: MacOS :: MacOS X
Classifier: Operating System :: Microsoft :: Windows
Requires-Python: >=3.6
